deep_dashboard/__init__.py
deep_dashboard/auth.py
deep_dashboard/config.py
deep_dashboard/deep_oc.py
deep_dashboard/log.py
deep_dashboard/opts.py
deep_dashboard/orchestrator.py
deep_dashboard/run.py
deep_dashboard/sla.py
deep_dashboard/tosca.py
deep_dashboard/utils.py
deep_dashboard/version.py
deep_dashboard/handlers/__init__.py
deep_dashboard/handlers/base.py
deep_dashboard/handlers/deployments.py
deep_dashboard/handlers/modules.py
deep_dashboard/static/bootstrap/Bootstrap-Confirmation-2/.editorconfig
deep_dashboard/static/bootstrap/Bootstrap-Confirmation-2/.gitignore
deep_dashboard/static/bootstrap/Bootstrap-Confirmation-2/Gruntfile.js
deep_dashboard/static/bootstrap/Bootstrap-Confirmation-2/README.md
deep_dashboard/static/bootstrap/Bootstrap-Confirmation-2/bootstrap-confirmation.js
deep_dashboard/static/bootstrap/Bootstrap-Confirmation-2/bootstrap-confirmation.min.js
deep_dashboard/static/bootstrap/Bootstrap-Confirmation-2/bower.json
deep_dashboard/static/bootstrap/Bootstrap-Confirmation-2/package.json
deep_dashboard/static/bootstrap/Bootstrap-Confirmation-2/example/index.html
deep_dashboard/static/css/screen.css
deep_dashboard/static/images/deep-cloud.png
deep_dashboard/static/images/logo-deep-solid-white.png
deep_dashboard/static/images/logo-deep.png
deep_dashboard/static/images/logo-ec.png
deep_dashboard/static/images/network.png
deep_dashboard/static/images/favicon/android-icon-192x192.png
deep_dashboard/static/images/favicon/apple-icon-114x114.png
deep_dashboard/static/images/favicon/apple-icon-120x120.png
deep_dashboard/static/images/favicon/apple-icon-144x144.png
deep_dashboard/static/images/favicon/apple-icon-152x152.png
deep_dashboard/static/images/favicon/apple-icon-180x180.png
deep_dashboard/static/images/favicon/apple-icon-57x57.png
deep_dashboard/static/images/favicon/apple-icon-60x60.png
deep_dashboard/static/images/favicon/apple-icon-72x72.png
deep_dashboard/static/images/favicon/apple-icon-76x76.png
deep_dashboard-0.7.0.dist-info/LICENSE
deep_dashboard-0.7.0.dist-info/METADATA
deep_dashboard-0.7.0.dist-info/WHEEL
deep_dashboard-0.7.0.dist-info/entry_points.txt
deep_dashboard-0.7.0.dist-info/pbr.json
deep_dashboard-0.7.0.dist-info/top_level.txt
deep_dashboard-0.7.0.dist-info/RECORD
