Metadata-Version: 2.1
Name: deep-dashboard
Version: 0.7.0
Summary: This project is the dashboard to interact with the DEEP services.
Home-page: https://gitlab.ifca.es/deep/deep-dashboard
Author: Alvaro Lopez Garcia
Author-email: aloga@ifca.unican.es
License: Apache-2
Project-URL: Bug Tracker, https://gitlab.ifca.es/deep/deep-dashboard/issues
Platform: UNKNOWN
Classifier: Development Status :: 5 - Production/Stable
Classifier: Environment :: Console
Classifier: Environment :: Web Environment
Classifier: Intended Audience :: Developers
Classifier: Intended Audience :: Information Technology
Classifier: Intended Audience :: Science/Research
Classifier: Intended Audience :: System Administrators
Classifier: License :: OSI Approved :: Apache Software License
Classifier: Operating System :: OS Independent
Classifier: Programming Language :: Python
Classifier: Programming Language :: Python :: 3
Classifier: Programming Language :: Python :: 3.6
Classifier: Programming Language :: Python :: 3.7
Classifier: Programming Language :: Python :: 3.8
Classifier: Topic :: Internet :: WWW/HTTP
Requires-Python: >=3.8
Requires-Dist: aioauth-client
Requires-Dist: aiocache[memcached]
Requires-Dist: aiohttp[speedups] (>=3.6.2)
Requires-Dist: aiohttp-jinja2
Requires-Dist: aiohttp-security
Requires-Dist: aiohttp-session[aiomcache]
Requires-Dist: aiohttp-session[secure]
Requires-Dist: aiohttp-session-flash
Requires-Dist: aiojobs
Requires-Dist: aiomcache
Requires-Dist: cryptography
Requires-Dist: gitpython
Requires-Dist: jinja2
Requires-Dist: markdown
Requires-Dist: orpy (>=1.0.1)
Requires-Dist: oslo.concurrency (>=4.4.0)
Requires-Dist: oslo.config (>=2.3.0)
Requires-Dist: oslo.log (>=1.8.0)
Requires-Dist: pbr (>=4.1.0)
Requires-Dist: pyyaml
